{
	"name": "building-blocks/author",
	"category": "common",
	"attributes": {
		"name": {
			"type": "string",
			"selector": ".wp-block-building-blocks-author__name"
		},
		"biography": {
			"type": "array",
			"source": "children",
			"selector": ".wp-block-building-blocks-author__biography"
		},
		"mediaID": {
			"type": "number"
		},
		"mediaURL": {
			"type": "string",
			"source": "attribute",
			"selector": "img",
			"attribute": "src"
		},
		"mediaALT": {
			"type": "string",
			"source": "attribute",
			"selector": "img",
			"attribute": "alt"
		}
	}
}
